{
  "filters": [
    {
      "goblin_cave": {
        "blue_Portal": [
          [190, 20],
          [250, 145],
          [300, 267],
          [490, 200],
          [15, 190],
          [90, 385],
          [200, 390],
          [245, 550]
        ],
        "red_Portal": [
          [190, 20],
          [250, 145],
          [300, 267],
          [490, 200],
          [15, 190],
          [90, 385],
          [200, 390],
          [245, 550]
        ],
        "bosses": [
          [420, 390],
          [175, 140]
        ],
        "sanctuary": [
          [60, 60],
          [320, 120],
          [210, 300],
          [450, 230]
        ]
      }
    }
  ]
}
